k8smap/__init__.py
k8smap/main.py
k8smap-0.1.1.dist-info/entry_points.txt
k8smap-0.1.1.dist-info/LICENSE
k8smap-0.1.1.dist-info/WHEEL
k8smap-0.1.1.dist-info/METADATA
k8smap-0.1.1.dist-info/RECORD
