Metadata-Version: 2.1
Name: k8smap
Version: 0.1.1
Summary: 
License: MIT
Author: Paul Beck
Requires-Python: >=3.9,<4.0
Classifier: License :: OSI Approved :: MIT License
Classifier: Programming Language :: Python :: 3
Classifier: Programming Language :: Python :: 3.9
Classifier: Programming Language :: Python :: 3.10
Classifier: Programming Language :: Python :: 3.11
Requires-Dist: black (>=22.12.0,<23.0.0)
Requires-Dist: click (>=8.1.3,<9.0.0)
Requires-Dist: flake8 (>=6.0.0,<7.0.0)
Requires-Dist: mypy (>=0.991,<0.992)
Requires-Dist: pyyaml (>=6.0,<7.0)
